pyup_tools-0.1.4.dist-info/DESCRIPTION.rst
pyup_tools-0.1.4.dist-info/METADATA
pyup_tools-0.1.4.dist-info/RECORD
pyup_tools-0.1.4.dist-info/WHEEL
pyup_tools-0.1.4.dist-info/entry_points.txt
pyup_tools-0.1.4.dist-info/metadata.json
pyup_tools-0.1.4.dist-info/top_level.txt
pyuptools/__init__.py
pyuptools/cli.py
