Metadata-Version: 2.0
Name: pyup-tools
Version: 0.1.4
Summary: Tools for pyup.io
Home-page: https://github.com/pyupio/pyup-tools
Author: pyup.io
Author-email: support@pyup.io
License: MIT
Platform: UNKNOWN
Classifier: Development Status :: 2 - Pre-Alpha
Classifier: Programming Language :: Python
Classifier: Programming Language :: Python :: 2
Classifier: Programming Language :: Python :: 2.7
Classifier: Programming Language :: Python :: 3
Classifier: Programming Language :: Python :: 3.4
Classifier: Programming Language :: Python :: 3.5
Requires-Dist: click
Requires-Dist: colorama
Requires-Dist: requests
